trainutils/__init__.py
trainutils/curves.py
trainutils/greeting.py
trainutils/greeting.txt
trainutils/utils/__init__.py
trainutils/utils/math.py
trainutils-1.1.0.dist-info/METADATA
trainutils-1.1.0.dist-info/WHEEL
trainutils-1.1.0.dist-info/top_level.txt
trainutils-1.1.0.dist-info/RECORD
