Metadata-Version: 2.1
Name: trainutils
Version: 1.1.0
Summary: Simple train utils - a very elementary but formal version 1.0.0 is available now
Home-page: https://github.com/pengyang486868/trainutils
Author: Yang Peng
Author-email: 854525261@qq.com
Maintainer: Yang Peng
Maintainer-email: 854525261@qq.com
License: BSD License
Platform: all
Classifier: Development Status :: 4 - Beta
Classifier: Operating System :: OS Independent
Classifier: Intended Audience :: Developers
Classifier: License :: OSI Approved :: BSD License
Classifier: Programming Language :: Python
Classifier: Programming Language :: Python :: Implementation
Classifier: Programming Language :: Python :: 2
Classifier: Programming Language :: Python :: 2.7
Classifier: Programming Language :: Python :: 3
Classifier: Programming Language :: Python :: 3.4
Classifier: Programming Language :: Python :: 3.5
Classifier: Programming Language :: Python :: 3.6
Classifier: Topic :: Software Development :: Libraries
Requires-Dist: numpy
